codex_autotest/__init__.py
codex_autotest/cli.py
codex_autotest/config.py
codex_autotest/openai_client.py
codex_autotest-0.2.0.dist-info/licenses/LICENSE
tests/__init__.py
tests/test_cli.py
tests/test_config.py
codex_autotest-0.2.0.dist-info/METADATA
codex_autotest-0.2.0.dist-info/WHEEL
codex_autotest-0.2.0.dist-info/entry_points.txt
codex_autotest-0.2.0.dist-info/top_level.txt
codex_autotest-0.2.0.dist-info/RECORD
